deceptionlogic/__init__.py
deceptionlogic/api/__init__.py
deceptionlogic/api/client.py
deceptionlogic/aws/__init__.py
deceptionlogic/aws/ec2.py
deceptionlogic-1.4.0.data/scripts/deception
deceptionlogic-1.4.0.dist-info/LICENSE
deceptionlogic-1.4.0.dist-info/METADATA
deceptionlogic-1.4.0.dist-info/WHEEL
deceptionlogic-1.4.0.dist-info/top_level.txt
deceptionlogic-1.4.0.dist-info/RECORD
