Metadata-Version: 2.1
Name: deceptionlogic
Version: 1.4.0
Summary: A python wrapper and CLI tool for the Deception Logic API.
Home-page: http://deceptionlogic.com
Download-URL: https://github.com/deceptionlogic/deception-api
Author: Deception Logic, Inc.
Author-email: info@deceptionlogic.com
License: MIT
Keywords: wrapper library deception logic api cli
Classifier: Intended Audience :: Developers
Classifier: Topic :: Software Development :: Libraries :: Python Modules
Classifier: Programming Language :: Python :: 2.7
Classifier: License :: OSI Approved :: MIT License
License-File: LICENSE
Requires-Dist: future
Requires-Dist: requests
Requires-Dist: boto3
